<?xml version="1.0" encoding="UTF-8" standalone="yes"?>
<sst xmlns="http://schemas.openxmlformats.org/spreadsheetml/2006/main" count="152" uniqueCount="39"><si><t>源语言</t></si><si><t>目标语言</t></si><si><t>原文</t></si><si><t>译文</t></si><si><t>该词汇是否翻译</t></si><si><t>该词汇是否区分大小写</t></si><si><t>英文</t></si><si><t>中文</t></si><si><t>是</t></si><si><t>否</t></si><si><t>procedure</t><phoneticPr fontId="1" type="noConversion"/></si><si><t>igniter</t><phoneticPr fontId="1" type="noConversion"/></si><si><t>level</t><phoneticPr fontId="1" type="noConversion"/></si><si><t>流程</t><phoneticPr fontId="1" type="noConversion"/></si><si><t>打火石</t><phoneticPr fontId="1" type="noConversion"/></si><si><t>等级</t><phoneticPr fontId="1" type="noConversion"/></si><si><t>block</t><phoneticPr fontId="1" type="noConversion"/></si><si><t>方块</t><phoneticPr fontId="1" type="noConversion"/></si><si><t>shulker</t><phoneticPr fontId="1" type="noConversion"/></si><si><t>潜影贝</t><phoneticPr fontId="1" type="noConversion"/></si><si><t>Minecraft</t><phoneticPr fontId="1" type="noConversion"/></si><si><t>step height</t></si><si><t>行走高度</t><phoneticPr fontId="1" type="noConversion"/></si><si><t>实体</t><phoneticPr fontId="1" type="noConversion"/></si><si><t>entity</t><phoneticPr fontId="1" type="noConversion"/></si><si><t>condition</t></si><si><t>条件</t><phoneticPr fontId="1" type="noConversion"/></si><si><t>values</t></si><si><t>数值</t><phoneticPr fontId="1" type="noConversion"/></si><si><t>maximal age</t></si><si><t>最大时长</t><phoneticPr fontId="1" type="noConversion"/></si><si><t>expire</t></si><si><t>消失</t><phoneticPr fontId="1" type="noConversion"/></si><si><t>tick</t><phoneticPr fontId="1" type="noConversion"/></si><si><t>游戏刻</t><phoneticPr fontId="1" type="noConversion"/></si><si><t>fluid drips</t><phoneticPr fontId="1" type="noConversion"/></si><si><t>液体滴落粒子</t><phoneticPr fontId="1" type="noConversion"/></si><si><t>mipmapping</t><phoneticPr fontId="1" type="noConversion"/></si><si><t>多级纹理映射</t><phoneticPr fontId="1" type="noConversion"/></si></sst>